{
  "parent": "minecraft:recipes/root",
  "rewards": {
    "recipes": [
      "minecraft:red_dye_from_poppy"
    ]
  },
  "criteria": {
    "has_poppy": {
      "trigger": "minecraft:inventory_changed",
      "conditions": {
        "items": [
          {
            "items": [
              "minecraft:poppy"
            ]
          }
        ]
      }
    },
    "has_the_recipe": {
      "trigger": "minecraft:recipe_unlocked",
      "conditions": {
        "recipe": "minecraft:red_dye_from_poppy"
      }
    }
  },
  "requirements": [
    [
      "has_poppy",
      "has_the_recipe"
    ]
  ]
}